ttrpg_core/__about__.py
ttrpg_core/__init__.py
ttrpg_core-0.0.1.dist-info/METADATA
ttrpg_core-0.0.1.dist-info/WHEEL
ttrpg_core-0.0.1.dist-info/licenses/LICENSE.txt
ttrpg_core-0.0.1.dist-info/RECORD
