Metadata-Version: 2.1
Name: ttrpg-core
Version: 0.0.1
Summary: Tools for tabletop role-playing games
Project-URL: Documentation, https://github.com/TTRPG-Dev/ttrpg-core#readme
Project-URL: Issues, https://github.com/TTRPG-Dev/ttrpg-core/issues
Project-URL: Source, https://github.com/TTRPG-Dev/ttrpg-core
Author-email: Quigley Malcolm <tqmalcolm@protonmail.com>
License-Expression: MIT
License-File: LICENSE.txt
Classifier: Development Status :: 4 - Beta
Classifier: Programming Language :: Python
Classifier: Programming Language :: Python :: 3.7
Classifier: Programming Language :: Python :: 3.8
Classifier: Programming Language :: Python :: 3.9
Classifier: Programming Language :: Python :: 3.10
Classifier: Programming Language :: Python :: 3.11
Classifier: Programming Language :: Python :: Implementation :: CPython
Classifier: Programming Language :: Python :: Implementation :: PyPy
Requires-Python: >=3.8
